[	
	{
		"agency": "Greyhealth Group/Sudler", 
		"title": "Living Nightmare: In Their Shoes" 
	},
	{
		"agency": "McCann Health", 
		"title": "Poo Romance" 
	}, 
	{
		"agency": "McCann Health", 
		"title": "Healthy Christmas Card" 
	}, 
	{
		"agency": "Ogilvy CommonHealth", 
		"title": "Tough to break free" 
	},
	{
		"agency": "Ogilvy CommonHealth", 
		"title": "The Stool Expert" 
	},
	{
		"agency": "Saatchi & Saatchi Wellness", 
		"title": "Blown out of action" 
	},
	{
		"agency": "Saatchi & Saatchi Wellness", 
		"title": "Protected Wallet" 
	},
	{
		"agency": "ShowPony", 
		"title": "Waiting is not an emergency" 
	},
	{
		"agency": "Ward6", 
		"title": "Abandon the Fan" 
	},
	{
		"agency": "Ward6", 
		"title": "The Happiest Sound in the World" 
	}	
]